opensymbiose/__init__.py
opensymbiose/config.py
opensymbiose/main.py
opensymbiose/agents/__init__.py
opensymbiose/agents/agent.py
opensymbiose/agents/agent_manager.py
opensymbiose/agents/create_agents.py
opensymbiose/agents/test_agent_manager.py
opensymbiose/gradio/app.py
opensymbiose-0.0.4.dist-info/METADATA
opensymbiose-0.0.4.dist-info/WHEEL
opensymbiose-0.0.4.dist-info/entry_points.txt
opensymbiose-0.0.4.dist-info/licenses/LICENSE
opensymbiose-0.0.4.dist-info/RECORD
